bgreference/__init__.py
bgreference/utils.py
bgreference-0.7.dist-info/LICENSE.txt
bgreference-0.7.dist-info/METADATA
bgreference-0.7.dist-info/WHEEL
bgreference-0.7.dist-info/entry_points.txt
bgreference-0.7.dist-info/top_level.txt
bgreference-0.7.dist-info/RECORD
