Metadata-Version: 2.1
Name: bgreference
Version: 0.7
Summary: Simple and fast genome reference retrieve
Home-page: https://bitbucket.org/bgframework/bgreference
Author: Barcelona Biomedical Genomics Lab
Author-email: UNKNOWN
License: Apache License 2
Download-URL: https://bitbucket.org/bgframework/bgreference/get/0.7.tar.gz
Platform: UNKNOWN
Requires-Dist: bgconfig (>=0.2)
Requires-Dist: bgdata (>=0.25)
